amilatest/__init__.py
amilatest/__version__.py
amilatest/cli.py
amilatest/main.py
amilatest-0.4.0.dist-info/LICENSE
amilatest-0.4.0.dist-info/METADATA
amilatest-0.4.0.dist-info/WHEEL
amilatest-0.4.0.dist-info/entry_points.txt
amilatest-0.4.0.dist-info/top_level.txt
amilatest-0.4.0.dist-info/RECORD
