Metadata-Version: 2.1
Name: amilatest
Version: 0.4.0
Summary: A dependency-analyzer for requirements.txt files
Home-page: https://github.com/schett-net/ami
Author: Nico Schett
Author-email: nicoschett@icloud.com
License: UNKNOWN
Project-URL: Bug Tracker, https://github.com/schett-net/ami/issues
Platform: UNKNOWN
Classifier: Programming Language :: Python :: 3
Classifier: License :: OSI Approved :: MIT License
Classifier: Operating System :: OS Independent
Requires-Python: >=3.6
Requires-Dist: alive-progress
Requires-Dist: enhancements
Requires-Dist: packaging
Requires-Dist: requirements-parser
Requires-Dist: tabulate
